mzpaf/__init__.py
mzpaf/annotation.py
mzpaf/reference.py
mzpaf/data/__init__.py
mzpaf-0.2.0b0.dist-info/LICENSE
mzpaf-0.2.0b0.dist-info/METADATA
mzpaf-0.2.0b0.dist-info/WHEEL
mzpaf-0.2.0b0.dist-info/top_level.txt
mzpaf-0.2.0b0.dist-info/RECORD
