Metadata-Version: 2.1
Name: mzpaf
Version: 0.2.0b0
Summary: HUPO-PSI Peptide peak annotation format
Classifier: License :: CC0 1.0 Universal (CC0 1.0) Public Domain Dedication
Classifier: Intended Audience :: Science/Research
Classifier: Programming Language :: Python :: 3 :: Only
Classifier: Topic :: Scientific/Engineering :: Bio-Informatics
Classifier: Development Status :: 4 - Beta
Requires: pyteomics
License-File: LICENSE
Provides-Extra: docs
Requires-Dist: sphinx; extra == "docs"
Requires-Dist: sphinx-rtd-theme; extra == "docs"
Requires-Dist: numpydoc<2,>=1; extra == "docs"
Requires-Dist: sphinx_click; extra == "docs"
Requires-Dist: myst-parser; extra == "docs"
Requires-Dist: sphinx-autobuild; extra == "docs"
Requires-Dist: pydata-sphinx-theme; extra == "docs"
